gqc_agent/__init__.py
gqc_agent/core/__init__.py
gqc_agent/core/orchestrator.py
gqc_agent/core/_constants/constants.py
gqc_agent/core/_intent_classifier/classifier.py
gqc_agent/core/_llm_models/gemini_client.py
gqc_agent/core/_llm_models/gemini_models.py
gqc_agent/core/_llm_models/gpt_client.py
gqc_agent/core/_llm_models/gpt_models.py
gqc_agent/core/_note_creator/note_creator.py
gqc_agent/core/_query_rephraser/rephraser.py
gqc_agent/core/_system_prompts/intent_classifier.md
gqc_agent/core/_system_prompts/loader.py
gqc_agent/core/_system_prompts/note_creator.md
gqc_agent/core/_system_prompts/query_rephraser.md
gqc_agent/core/_validations/input_validator.py
gqc_agent/core/_validations/model_validator.py
gqc_agent-1.0.3.dist-info/licenses/LICENSE
gqc_agent-1.0.3.dist-info/METADATA
gqc_agent-1.0.3.dist-info/WHEEL
gqc_agent-1.0.3.dist-info/top_level.txt
gqc_agent-1.0.3.dist-info/RECORD
