Metadata-Version: 2.4
Name: gqc-agent
Version: 1.0.3
Summary: GQC Agent provides a multi-agent AI pipeline for intent classification, query rephrasing, and note creation using GPT and Gemini models.
Author-email: BE Developers <be.dev@bigentities.com>
License: MIT
Keywords: gqc-agent,intent-classification,query-rephraser,notes-creator,openai-models,gemini-models
Classifier: Development Status :: 4 - Beta
Classifier: Intended Audience :: Developers
Classifier: License :: OSI Approved :: MIT License
Classifier: Programming Language :: Python :: 3
Classifier: Programming Language :: Python :: 3.11
Classifier: Programming Language :: Python :: 3.12
Classifier: Programming Language :: Python :: 3.13
Classifier: Programming Language :: Python :: 3 :: Only
Requires-Python: >=3.11
License-File: LICENSE
Requires-Dist: openai>=2.8.1
Requires-Dist: google-genai>=1.52.0
Requires-Dist: pydantic>=2.12.5
Requires-Dist: requests>=2.32.5
Requires-Dist: httpx>=0.28.1
Requires-Dist: anyio>=4.12.0
Dynamic: license-file
